icplot/__init__.py
icplot/cairo_interface.py
icplot/color.py
icplot/convert.py
icplot/image_utils.py
icplot/main_cli.py
icplot/mermaid.py
icplot/py.typed
icplot/scene.py
icplot/tex.py
icplot/tree.py
icplot/gantt/__init__.py
icplot/gantt/gantt.py
icplot/gantt/gantt_renderer.py
icplot/gantt/pgfgantt.py
icplot/geometry/__init__.py
icplot/geometry/base.py
icplot/geometry/operations.py
icplot/geometry/shapes.py
icplot/geometry/transform.py
icplot/graph/__init__.py
icplot/graph/axis.py
icplot/graph/generator.py
icplot/graph/matplotlib.py
icplot/graph/mpl.py
icplot/graph/plot.py
icplot/graph/plot_group.py
icplot/graph/series.py
icplot/graph/video.py
icplot/graph/vtk.py
icplot/mesh/__init__.py
icplot/mesh/cell.py
icplot/mesh/edge.py
icplot/mesh/mesh.py
icplot/mesh/operations.py
icplot/mesh/shapes.py
icplot/mesh/vertex.py
icplot/mesh/vtk.py
icplot/mesh/openfoam/__init__.py
icplot/mesh/openfoam/blockmesh.py
icplot/mesh/openfoam/foamfile.py
icplot/mesh/openfoam/polymesh.py
icplot/trace/__init__.py
icplot/trace/trace.py
icplot-0.2.4.dist-info/licenses/LICENSE
icplot-0.2.4.dist-info/METADATA
icplot-0.2.4.dist-info/WHEEL
icplot-0.2.4.dist-info/entry_points.txt
icplot-0.2.4.dist-info/top_level.txt
icplot-0.2.4.dist-info/RECORD
