Metadata-Version: 2.4
Name: icplot
Version: 0.2.4
Summary: Utilities for generating plots and graphics for technical reports.
Author-email: "James Grogan, Irish Centre for High End Computing" <james.grogan@ichec.ie>
Project-URL: Repository, https://git.ichec.ie/performance/toolshed/icplot
Project-URL: Homepage, https://git.ichec.ie/performance/toolshed/icplot
Keywords: Publishing,Technical Reports,Graphics
Classifier: Development Status :: 3 - Alpha
Classifier: Programming Language :: Python :: 3
Classifier: License :: OSI Approved :: GNU General Public License v3 or later (GPLv3+)
Classifier: Operating System :: OS Independent
Classifier: Topic :: System :: Distributed Computing
Requires-Python: >=3.10
License-File: LICENSE
Requires-Dist: wand
Requires-Dist: matplotlib
Requires-Dist: vtk
Requires-Dist: moviepy
Requires-Dist: scipy
Requires-Dist: iccore==0.2.3
Requires-Dist: graphviz
Provides-Extra: test
Requires-Dist: pytest; extra == "test"
Requires-Dist: pytest-cov; extra == "test"
Requires-Dist: pytest-sugar; extra == "test"
Requires-Dist: black; extra == "test"
Requires-Dist: mypy; extra == "test"
Requires-Dist: flake8; extra == "test"
Requires-Dist: pylint; extra == "test"
Provides-Extra: cairo
Requires-Dist: pycairo; extra == "cairo"
Requires-Dist: CairoSVG; extra == "cairo"
Dynamic: license-file
